jupyterhub_comments/__init__.py
jupyterhub_comments/_version.py
jupyterhub_comments/handlers.py
jupyterhub_comments/locale/ru_RU/LC_MESSAGES/jupyterhub_comments.json
jupyterhub_comments/locale/ru_RU/LC_MESSAGES/jupyterhub_comments.po
jupyterhub_comments-1.0.1.data/data/etc/jupyter/jupyter_server_config.d/jupyterhub_comments.json
jupyterhub_comments-1.0.1.data/data/share/jupyter/labextensions/jupyterhub-comments/package.json
jupyterhub_comments-1.0.1.data/data/share/jupyter/labextensions/jupyterhub-comments/static/262.3b02e209e182a45e7612.js
jupyterhub_comments-1.0.1.data/data/share/jupyter/labextensions/jupyterhub-comments/static/386.8af1377ebc78e3e3c452.js
jupyterhub_comments-1.0.1.data/data/share/jupyter/labextensions/jupyterhub-comments/static/633.69a6437424a15a74e153.js
jupyterhub_comments-1.0.1.data/data/share/jupyter/labextensions/jupyterhub-comments/static/728.76ab94e29281bacc1a11.js
jupyterhub_comments-1.0.1.data/data/share/jupyter/labextensions/jupyterhub-comments/static/remoteEntry.84e91326f8f1aa9af3d8.js
jupyterhub_comments-1.0.1.data/data/share/jupyter/labextensions/jupyterhub-comments/static/style.js
jupyterhub_comments-1.0.1.data/data/share/jupyter/labextensions/jupyterhub-comments/static/third-party-licenses.json
jupyterhub_comments-1.0.1.data/data/share/jupyter/labextensions/jupyterhub-comments/install.json
jupyterhub_comments-1.0.1.dist-info/METADATA
jupyterhub_comments-1.0.1.dist-info/WHEEL
jupyterhub_comments-1.0.1.dist-info/licenses/LICENSE
jupyterhub_comments-1.0.1.dist-info/RECORD
