Metadata-Version: 2.3
Name: jupyterhub_comments
Version: 1.0.1
Summary: A JupyterLab extension that allows adding comments to notebooks and documents in a multiuser environment.
Project-URL: Homepage, https://github.com/SausageLion/jupyterhub-comments
Project-URL: Bug Tracker, https://github.com/SausageLion/jupyterhub-comments/issues
Project-URL: Repository, https://github.com/SausageLion/jupyterhub-comments.git
Author-email: Vadim Arnold <vadim.arnold@bk.ru>
License: BSD 3-Clause License
License-File: LICENSE
Keywords: jupyter,jupyterlab,jupyterlab-extension
Classifier: Framework :: Jupyter
Classifier: Framework :: Jupyter :: JupyterLab
Classifier: Framework :: Jupyter :: JupyterLab :: 4
Classifier: Framework :: Jupyter :: JupyterLab :: Extensions
Classifier: Framework :: Jupyter :: JupyterLab :: Extensions :: Prebuilt
Classifier: License :: OSI Approved :: BSD License
Classifier: Programming Language :: Python
Classifier: Programming Language :: Python :: 3
Classifier: Programming Language :: Python :: 3.8
Classifier: Programming Language :: Python :: 3.9
Classifier: Programming Language :: Python :: 3.10
Classifier: Programming Language :: Python :: 3.11
Classifier: Programming Language :: Python :: 3.12
Requires-Python: >=3.8
Requires-Dist: jupyter-server<3,>=2.0.1
